CHANGES.txt
CONTRIBUTORS.txt
MANIFEST.in
README.rst
setup.py
acsone/__init__.py
acsone.recipe.odoo.pydev.egg-info/PKG-INFO
acsone.recipe.odoo.pydev.egg-info/SOURCES.txt
acsone.recipe.odoo.pydev.egg-info/dependency_links.txt
acsone.recipe.odoo.pydev.egg-info/entry_points.txt
acsone.recipe.odoo.pydev.egg-info/namespace_packages.txt
acsone.recipe.odoo.pydev.egg-info/not-zip-safe
acsone.recipe.odoo.pydev.egg-info/requires.txt
acsone.recipe.odoo.pydev.egg-info/top_level.txt
acsone/recipe/__init__.py
acsone/recipe/odoo/__init__.py
acsone/recipe/odoo/pydev/__init__.py
acsone/recipe/odoo/pydev/tests/__init__.py
acsone/recipe/odoo/pydev/tests/test_docs.py