Metadata-Version: 1.1
Name: acsone.recipe.odoo.pydev
Version: 1.0
Summary: A buildout recipe to install and configure a PyDev project for Openerp
Home-page: http://pypi.python.org/pypi/acsone.recipe.odoo.pydev
Author: ACSONE SA/NV
Author-email: laurent.mignon__at__acsone.eu
License: GPLv3+
Platform: UNKNOWN
Classifier: Framework :: Buildout :: Recipe
Classifier: Intended Audience :: Developers
Classifier: Intended Audience :: System Administrators
Classifier: License :: OSI Approved :: GNU Affero General Public License v3 or later (AGPLv3+)
Classifier: Topic :: Software Development :: Build Tools
Classifier: Topic :: Software Development :: Libraries :: Python Modules
